elixir/__init__.py
elixir/api/__init__.py
elixir/api/requests.py
elixir/config/__init__.py
elixir/config/constants.py
elixir/decorators/__init__.py
elixir/decorators/base.py
elixir/instruments.py
elixir/metrics/__init__.py
elixir/metrics/metrics.py
elixir/telemetry.py
elixir/tracing/__init__.py
elixir/tracing/context_manager.py
elixir/tracing/semconv.py
elixir/tracing/tracing.py
elixir/utils/__init__.py
elixir/utils/ipython.py
elixir/utils/string.py
elixir/utils/twilio.py
elixir/version.py
elixir_ai-0.1.3.dist-info/LICENSE
elixir_ai-0.1.3.dist-info/METADATA
elixir_ai-0.1.3.dist-info/WHEEL
elixir_ai-0.1.3.dist-info/RECORD
