Metadata-Version: 2.1
Name: elixir-ai
Version: 0.1.3
Summary: 
Author: Andrew Chang
Author-email: andrew@acalabs.xyz
Requires-Python: >=3.11,<4.0
Classifier: Programming Language :: Python :: 3
Classifier: Programming Language :: Python :: 3.11
Classifier: Programming Language :: Python :: 3.12
Requires-Dist: aioboto3 (>=13.0.0,<14.0.0)
Requires-Dist: aiohttp (>=3.9.5,<4.0.0)
Requires-Dist: colorama (>=0.4.6,<0.5.0)
Requires-Dist: ipython (>=8.25.0,<9.0.0)
Requires-Dist: opentelemetry-api (>=1.25.0,<2.0.0)
Requires-Dist: opentelemetry-exporter-otlp-proto-grpc (>=1.25.0,<2.0.0)
Requires-Dist: opentelemetry-exporter-otlp-proto-http (>=1.25.0,<2.0.0)
Requires-Dist: opentelemetry-instrumentation-anthropic (>=0.26.0,<0.27.0)
Requires-Dist: opentelemetry-instrumentation-bedrock (>=0.26.0,<0.27.0)
Requires-Dist: opentelemetry-instrumentation-chromadb (>=0.26.0,<0.27.0)
Requires-Dist: opentelemetry-instrumentation-cohere (>=0.26.0,<0.27.0)
Requires-Dist: opentelemetry-instrumentation-haystack (>=0.26.0,<0.27.0)
Requires-Dist: opentelemetry-instrumentation-langchain (>=0.26.0,<0.27.0)
Requires-Dist: opentelemetry-instrumentation-llamaindex (>=0.26.0,<0.27.0)
Requires-Dist: opentelemetry-instrumentation-milvus (>=0.26.0,<0.27.0)
Requires-Dist: opentelemetry-instrumentation-mistralai (>=0.26.0,<0.27.0)
Requires-Dist: opentelemetry-instrumentation-ollama (>=0.26.0,<0.27.0)
Requires-Dist: opentelemetry-instrumentation-openai (>=0.26.0,<0.27.0)
Requires-Dist: opentelemetry-instrumentation-pinecone (>=0.26.0,<0.27.0)
Requires-Dist: opentelemetry-instrumentation-qdrant (>=0.26.0,<0.27.0)
Requires-Dist: opentelemetry-instrumentation-replicate (>=0.26.0,<0.27.0)
Requires-Dist: opentelemetry-instrumentation-transformers (>=0.26.0,<0.27.0)
Requires-Dist: opentelemetry-instrumentation-vertexai (>=0.26.0,<0.27.0)
Requires-Dist: opentelemetry-instrumentation-watsonx (>=0.26.0,<0.27.0)
Requires-Dist: opentelemetry-instrumentation-weaviate (>=0.26.0,<0.27.0)
Requires-Dist: opentelemetry-sdk (>=1.24.0,<2.0.0)
Requires-Dist: opentelemetry-semantic-conventions-ai (>=0.3.6,<0.4.0)
Requires-Dist: posthog (>=3.5.0,<4.0.0)
Requires-Dist: python-dotenv (>=1.0.1,<2.0.0)
Requires-Dist: sentry-sdk (>=2.3.1,<3.0.0)
